basicblockchains_ecc/__init__.py
basicblockchains_ecc/cryptomath.py
basicblockchains_ecc/elliptic_curve.py
basicblockchains_ecc-2.2.0.dist-info/LICENSE.txt
basicblockchains_ecc-2.2.0.dist-info/METADATA
basicblockchains_ecc-2.2.0.dist-info/WHEEL
basicblockchains_ecc-2.2.0.dist-info/top_level.txt
basicblockchains_ecc-2.2.0.dist-info/RECORD
