Metadata-Version: 2.1
Name: basicblockchains-ecc
Version: 2.2.0
Summary: A class for elliptic curve cryptography
Author-email: Basic Blockchains <basicblockchains@gmail.com>
License: Copyright (c) 2022 Basic Blockchains        
Project-URL: Homepage, https://github.com/BasicBlockchains/ECC
Keywords: cryptography,elliptic curve,secp256k1,crypto
Classifier: License :: OSI Approved :: MIT License
Classifier: Programming Language :: Python
Classifier: Programming Language :: Python :: 3
Classifier: Programming Language :: Python :: 3.7
Classifier: Programming Language :: Python :: 3.8
Classifier: Programming Language :: Python :: 3.9
Classifier: Programming Language :: Python :: 3.10
Classifier: Development Status :: 5 - Production/Stable
Classifier: Intended Audience :: Developers
Classifier: Intended Audience :: Education
Classifier: Intended Audience :: Science/Research
Classifier: Intended Audience :: Other Audience
Classifier: Topic :: Security :: Cryptography
Requires-Python: >=3.7
License-File: LICENSE.txt
Requires-Dist: primefac
